{
  "total_count": 5,
  "workflow_runs": [
    {
      "id": 28773350448,
      "name": "Deploy Frontend",
      "node_id": "WFR_kwLOTO3gCM8AAAAGswZ8MA",
      "head_branch": "main",
      "head_sha": "f59a32a6758c900150b3309050c3083664faeef7",
      "path": ".github/workflows/deploy.yml",
      "display_title": "Fix CI toolchain action version",
      "run_number": 2,
      "event": "push",
      "status": "completed",
      "conclusion": "skipped",
      "workflow_id": 307823681,
      "check_suite_id": 77759318578,
      "check_suite_node_id": "CS_kwDOTO3gCM8AAAASGtEKMg",
      "url": "https://api.github.com/repos/Aryan132005/Steller-Yellowbelt/actions/runs/28773350448",
      "html_url": "https://github.com/Aryan132005/Steller-Yellowbelt/actions/runs/28773350448",
      "pull_requests": [

      ],
      "created_at": "2026-07-06T06:51:04Z",
      "updated_at": "2026-07-06T06:51:05Z",
      "actor": {
        "login": "Aryan132005",
        "id": 146818102,
        "node_id": "U_kgDOCMBENg",
        "avatar_url": "https://avatars.githubusercontent.com/u/146818102?v=4",
        "gravatar_id": "",
        "url": "https://api.github.com/users/Aryan132005",
        "html_url": "https://github.com/Aryan132005",
        "followers_url": "https://api.github.com/users/Aryan132005/followers",
        "following_url": "https://api.github.com/users/Aryan132005/following{/other_user}",
        "gists_url": "https://api.github.com/users/Aryan132005/gists{/gist_id}",
        "starred_url": "https://api.github.com/users/Aryan132005/starred{/owner}{/repo}",
        "subscriptions_url": "https://api.github.com/users/Aryan132005/subscriptions",
        "organizations_url": "https://api.github.com/users/Aryan132005/orgs",
        "repos_url": "https://api.github.com/users/Aryan132005/repos",
        "events_url": "https://api.github.com/users/Aryan132005/events{/privacy}",
        "received_events_url": "https://api.github.com/users/Aryan132005/received_events",
        "type": "User",
        "user_view_type": "public",
        "site_admin": false
      },
      "run_attempt": 1,
      "referenced_workflows": [

      ],
      "run_started_at": "2026-07-06T06:51:04Z",
      "triggering_actor": {
        "login": "Aryan132005",
        "id": 146818102,
        "node_id": "U_kgDOCMBENg",
        "avatar_url": "https://avatars.githubusercontent.com/u/146818102?v=4",
        "gravatar_id": "",
        "url": "https://api.github.com/users/Aryan132005",
        "html_url": "https://github.com/Aryan132005",
        "followers_url": "https://api.github.com/users/Aryan132005/followers",
        "following_url": "https://api.github.com/users/Aryan132005/following{/other_user}",
        "gists_url": "https://api.github.com/users/Aryan132005/gists{/gist_id}",
        "starred_url": "https://api.github.com/users/Aryan132005/starred{/owner}{/repo}",
        "subscriptions_url": "https://api.github.com/users/Aryan132005/subscriptions",
        "organizations_url": "https://api.github.com/users/Aryan132005/orgs",
        "repos_url": "https://api.github.com/users/Aryan132005/repos",
        "events_url": "https://api.github.com/users/Aryan132005/events{/privacy}",
        "received_events_url": "https://api.github.com/users/Aryan132005/received_events",
        "type": "User",
        "user_view_type": "public",
        "site_admin": false
      },
      "jobs_url": "https://api.github.com/repos/Aryan132005/Steller-Yellowbelt/actions/runs/28773350448/jobs",
      "logs_url": "https://api.github.com/repos/Aryan132005/Steller-Yellowbelt/actions/runs/28773350448/logs",
      "check_suite_url": "https://api.github.com/repos/Aryan132005/Steller-Yellowbelt/check-suites/77759318578",
      "artifacts_url": "https://api.github.com/repos/Aryan132005/Steller-Yellowbelt/actions/runs/28773350448/artifacts",
      "cancel_url": "https://api.github.com/repos/Aryan132005/Steller-Yellowbelt/actions/runs/28773350448/cancel",
      "rerun_url": "https://api.github.com/repos/Aryan132005/Steller-Yellowbelt/actions/runs/28773350448/rerun",
      "previous_attempt_url": null,
      "workflow_url": "https://api.github.com/repos/Aryan132005/Steller-Yellowbelt/actions/workflows/307823681",
      "head_commit": {
        "id": "f59a32a6758c900150b3309050c3083664faeef7",
        "tree_id": "149e17eefe885442401c3f1ba19a08c0212fc0f9",
        "message": "Fix CI toolchain action version",
        "timestamp": "2026-07-06T06:50:56Z",
        "author": {
          "name": "Aryan Saini",
          "email": "aryansaini132005@gmail.com"
        },
        "committer": {
          "name": "Aryan Saini",
          "email": "aryansaini132005@gmail.com"
        }
      },
      "repository": {
        "id": 1290657800,
        "node_id": "R_kgDOTO3gCA",
        "name": "Steller-Yellowbelt",
        "full_name": "Aryan132005/Steller-Yellowbelt",
        "private": false,
        "owner": {
          "login": "Aryan132005",
          "id": 146818102,
          "node_id": "U_kgDOCMBENg",
          "avatar_url": "https://avatars.githubusercontent.com/u/146818102?v=4",
          "gravatar_id": "",
          "url": "https://api.github.com/users/Aryan132005",
          "html_url": "https://github.com/Aryan132005",
          "followers_url": "https://api.github.com/users/Aryan132005/followers",
          "following_url": "https://api.github.com/users/Aryan132005/following{/other_user}",
          "gists_url": "https://api.github.com/users/Aryan132005/gists{/gist_id}",
          "starred_url": "https://api.github.com/users/Aryan132005/starred{/owner}{/repo}",
          "subscriptions_url": "https://api.github.com/users/Aryan132005/subscriptions",
          "organizations_url": "https://api.github.com/users/Aryan132005/orgs",
          "repos_url": "https://api.github.com/users/Aryan132005/repos",
          "events_url": "https://api.github.com/users/Aryan132005/events{/privacy}",
          "received_events_url": "https://api.github.com/users/Aryan132005/received_events",
          "type": "User",
          "user_view_type": "public",
          "site_admin": false
        },
        "html_url": "https://github.com/Aryan132005/Steller-Yellowbelt",
        "description": null,
        "fork": false,
        "url": "https://api.github.com/repos/Aryan132005/Steller-Yellowbelt",
        "forks_url": "https://api.github.com/repos/Aryan132005/Steller-Yellowbelt/forks",
        "keys_url": "https://api.github.com/repos/Aryan132005/Steller-Yellowbelt/keys{/key_id}",
        "collaborators_url": "https://api.github.com/repos/Aryan132005/Steller-Yellowbelt/collaborators{/collaborator}",
        "teams_url": "https://api.github.com/repos/Aryan132005/Steller-Yellowbelt/teams",
        "hooks_url": "https://api.github.com/repos/Aryan132005/Steller-Yellowbelt/hooks",
        "issue_events_url": "https://api.github.com/repos/Aryan132005/Steller-Yellowbelt/issues/events{/number}",
        "events_url": "https://api.github.com/repos/Aryan132005/Steller-Yellowbelt/events",
        "assignees_url": "https://api.github.com/repos/Aryan132005/Steller-Yellowbelt/assignees{/user}",
        "branches_url": "https://api.github.com/repos/Aryan132005/Steller-Yellowbelt/branches{/branch}",
        "tags_url": "https://api.github.com/repos/Aryan132005/Steller-Yellowbelt/tags",
        "blobs_url": "https://api.github.com/repos/Aryan132005/Steller-Yellowbelt/git/blobs{/sha}",
        "git_tags_url": "https://api.github.com/repos/Aryan132005/Steller-Yellowbelt/git/tags{/sha}",
        "git_refs_url": "https://api.github.com/repos/Aryan132005/Steller-Yellowbelt/git/refs{/sha}",
        "trees_url": "https://api.github.com/repos/Aryan132005/Steller-Yellowbelt/git/trees{/sha}",
        "statuses_url": "https://api.github.com/repos/Aryan132005/Steller-Yellowbelt/statuses/{sha}",
        "languages_url": "https://api.github.com/repos/Aryan132005/Steller-Yellowbelt/languages",
        "stargazers_url": "https://api.github.com/repos/Aryan132005/Steller-Yellowbelt/stargazers",
        "contributors_url": "https://api.github.com/repos/Aryan132005/Steller-Yellowbelt/contributors",
        "subscribers_url": "https://api.github.com/repos/Aryan132005/Steller-Yellowbelt/subscribers",
        "subscription_url": "https://api.github.com/repos/Aryan132005/Steller-Yellowbelt/subscription",
        "commits_url": "https://api.github.com/repos/Aryan132005/Steller-Yellowbelt/commits{/sha}",
        "git_commits_url": "https://api.github.com/repos/Aryan132005/Steller-Yellowbelt/git/commits{/sha}",
        "comments_url": "https://api.github.com/repos/Aryan132005/Steller-Yellowbelt/comments{/number}",
        "issue_comment_url": "https://api.github.com/repos/Aryan132005/Steller-Yellowbelt/issues/comments{/number}",
        "contents_url": "https://api.github.com/repos/Aryan132005/Steller-Yellowbelt/contents/{+path}",
        "compare_url": "https://api.github.com/repos/Aryan132005/Steller-Yellowbelt/compare/{base}...{head}",
        "merges_url": "https://api.github.com/repos/Aryan132005/Steller-Yellowbelt/merges",
        "archive_url": "https://api.github.com/repos/Aryan132005/Steller-Yellowbelt/{archive_format}{/ref}",
        "downloads_url": "https://api.github.com/repos/Aryan132005/Steller-Yellowbelt/downloads",
        "issues_url": "https://api.github.com/repos/Aryan132005/Steller-Yellowbelt/issues{/number}",
        "pulls_url": "https://api.github.com/repos/Aryan132005/Steller-Yellowbelt/pulls{/number}",
        "milestones_url": "https://api.github.com/repos/Aryan132005/Steller-Yellowbelt/milestones{/number}",
        "notifications_url": "https://api.github.com/repos/Aryan132005/Steller-Yellowbelt/notifications{?since,all,participating}",
        "labels_url": "https://api.github.com/repos/Aryan132005/Steller-Yellowbelt/labels{/name}",
        "releases_url": "https://api.github.com/repos/Aryan132005/Steller-Yellowbelt/releases{/id}",
        "deployments_url": "https://api.github.com/repos/Aryan132005/Steller-Yellowbelt/deployments"
      },
      "head_repository": {
        "id": 1290657800,
        "node_id": "R_kgDOTO3gCA",
        "name": "Steller-Yellowbelt",
        "full_name": "Aryan132005/Steller-Yellowbelt",
        "private": false,
        "owner": {
          "login": "Aryan132005",
          "id": 146818102,
          "node_id": "U_kgDOCMBENg",
          "avatar_url": "https://avatars.githubusercontent.com/u/146818102?v=4",
          "gravatar_id": "",
          "url": "https://api.github.com/users/Aryan132005",
          "html_url": "https://github.com/Aryan132005",
          "followers_url": "https://api.github.com/users/Aryan132005/followers",
          "following_url": "https://api.github.com/users/Aryan132005/following{/other_user}",
          "gists_url": "https://api.github.com/users/Aryan132005/gists{/gist_id}",
          "starred_url": "https://api.github.com/users/Aryan132005/starred{/owner}{/repo}",
          "subscriptions_url": "https://api.github.com/users/Aryan132005/subscriptions",
          "organizations_url": "https://api.github.com/users/Aryan132005/orgs",
          "repos_url": "https://api.github.com/users/Aryan132005/repos",
          "events_url": "https://api.github.com/users/Aryan132005/events{/privacy}",
          "received_events_url": "https://api.github.com/users/Aryan132005/received_events",
          "type": "User",
          "user_view_type": "public",
          "site_admin": false
        },
        "html_url": "https://github.com/Aryan132005/Steller-Yellowbelt",
        "description": null,
        "fork": false,
        "url": "https://api.github.com/repos/Aryan132005/Steller-Yellowbelt",
        "forks_url": "https://api.github.com/repos/Aryan132005/Steller-Yellowbelt/forks",
        "keys_url": "https://api.github.com/repos/Aryan132005/Steller-Yellowbelt/keys{/key_id}",
        "collaborators_url": "https://api.github.com/repos/Aryan132005/Steller-Yellowbelt/collaborators{/collaborator}",
        "teams_url": "https://api.github.com/repos/Aryan132005/Steller-Yellowbelt/teams",
        "hooks_url": "https://api.github.com/repos/Aryan132005/Steller-Yellowbelt/hooks",
        "issue_events_url": "https://api.github.com/repos/Aryan132005/Steller-Yellowbelt/issues/events{/number}",
        "events_url": "https://api.github.com/repos/Aryan132005/Steller-Yellowbelt/events",
        "assignees_url": "https://api.github.com/repos/Aryan132005/Steller-Yellowbelt/assignees{/user}",
        "branches_url": "https://api.github.com/repos/Aryan132005/Steller-Yellowbelt/branches{/branch}",
        "tags_url": "https://api.github.com/repos/Aryan132005/Steller-Yellowbelt/tags",
        "blobs_url": "https://api.github.com/repos/Aryan132005/Steller-Yellowbelt/git/blobs{/sha}",
        "git_tags_url": "https://api.github.com/repos/Aryan132005/Steller-Yellowbelt/git/tags{/sha}",
        "git_refs_url": "https://api.github.com/repos/Aryan132005/Steller-Yellowbelt/git/refs{/sha}",
        "trees_url": "https://api.github.com/repos/Aryan132005/Steller-Yellowbelt/git/trees{/sha}",
        "statuses_url": "https://api.github.com/repos/Aryan132005/Steller-Yellowbelt/statuses/{sha}",
        "languages_url": "https://api.github.com/repos/Aryan132005/Steller-Yellowbelt/languages",
        "stargazers_url": "https://api.github.com/repos/Aryan132005/Steller-Yellowbelt/stargazers",
        "contributors_url": "https://api.github.com/repos/Aryan132005/Steller-Yellowbelt/contributors",
        "subscribers_url": "https://api.github.com/repos/Aryan132005/Steller-Yellowbelt/subscribers",
        "subscription_url": "https://api.github.com/repos/Aryan132005/Steller-Yellowbelt/subscription",
        "commits_url": "https://api.github.com/repos/Aryan132005/Steller-Yellowbelt/commits{/sha}",
        "git_commits_url": "https://api.github.com/repos/Aryan132005/Steller-Yellowbelt/git/commits{/sha}",
        "comments_url": "https://api.github.com/repos/Aryan132005/Steller-Yellowbelt/comments{/number}",
        "issue_comment_url": "https://api.github.com/repos/Aryan132005/Steller-Yellowbelt/issues/comments{/number}",
        "contents_url": "https://api.github.com/repos/Aryan132005/Steller-Yellowbelt/contents/{+path}",
        "compare_url": "https://api.github.com/repos/Aryan132005/Steller-Yellowbelt/compare/{base}...{head}",
        "merges_url": "https://api.github.com/repos/Aryan132005/Steller-Yellowbelt/merges",
        "archive_url": "https://api.github.com/repos/Aryan132005/Steller-Yellowbelt/{archive_format}{/ref}",
        "downloads_url": "https://api.github.com/repos/Aryan132005/Steller-Yellowbelt/downloads",
        "issues_url": "https://api.github.com/repos/Aryan132005/Steller-Yellowbelt/issues{/number}",
        "pulls_url": "https://api.github.com/repos/Aryan132005/Steller-Yellowbelt/pulls{/number}",
        "milestones_url": "https://api.github.com/repos/Aryan132005/Steller-Yellowbelt/milestones{/number}",
        "notifications_url": "https://api.github.com/repos/Aryan132005/Steller-Yellowbelt/notifications{?since,all,participating}",
        "labels_url": "https://api.github.com/repos/Aryan132005/Steller-Yellowbelt/labels{/name}",
        "releases_url": "https://api.github.com/repos/Aryan132005/Steller-Yellowbelt/releases{/id}",
        "deployments_url": "https://api.github.com/repos/Aryan132005/Steller-Yellowbelt/deployments"
      }
    },
    {
      "id": 28773350443,
      "name": "CI",
      "node_id": "WFR_kwLOTO3gCM8AAAAGswZ8Kw",
      "head_branch": "main",
      "head_sha": "f59a32a6758c900150b3309050c3083664faeef7",
      "path": ".github/workflows/ci.yml",
      "display_title": "Fix CI toolchain action version",
      "run_number": 2,
      "event": "push",
      "status": "completed",
      "conclusion": "failure",
      "workflow_id": 307823677,
      "check_suite_id": 77759318560,
      "check_suite_node_id": "CS_kwDOTO3gCM8AAAASGtEKIA",
      "url": "https://api.github.com/repos/Aryan132005/Steller-Yellowbelt/actions/runs/28773350443",
      "html_url": "https://github.com/Aryan132005/Steller-Yellowbelt/actions/runs/28773350443",
      "pull_requests": [

      ],
      "created_at": "2026-07-06T06:51:04Z",
      "updated_at": "2026-07-06T06:52:03Z",
      "actor": {
        "login": "Aryan132005",
        "id": 146818102,
        "node_id": "U_kgDOCMBENg",
        "avatar_url": "https://avatars.githubusercontent.com/u/146818102?v=4",
        "gravatar_id": "",
        "url": "https://api.github.com/users/Aryan132005",
        "html_url": "https://github.com/Aryan132005",
        "followers_url": "https://api.github.com/users/Aryan132005/followers",
        "following_url": "https://api.github.com/users/Aryan132005/following{/other_user}",
        "gists_url": "https://api.github.com/users/Aryan132005/gists{/gist_id}",
        "starred_url": "https://api.github.com/users/Aryan132005/starred{/owner}{/repo}",
        "subscriptions_url": "https://api.github.com/users/Aryan132005/subscriptions",
        "organizations_url": "https://api.github.com/users/Aryan132005/orgs",
        "repos_url": "https://api.github.com/users/Aryan132005/repos",
        "events_url": "https://api.github.com/users/Aryan132005/events{/privacy}",
        "received_events_url": "https://api.github.com/users/Aryan132005/received_events",
        "type": "User",
        "user_view_type": "public",
        "site_admin": false
      },
      "run_attempt": 1,
      "referenced_workflows": [

      ],
      "run_started_at": "2026-07-06T06:51:04Z",
      "triggering_actor": {
        "login": "Aryan132005",
        "id": 146818102,
        "node_id": "U_kgDOCMBENg",
        "avatar_url": "https://avatars.githubusercontent.com/u/146818102?v=4",
        "gravatar_id": "",
        "url": "https://api.github.com/users/Aryan132005",
        "html_url": "https://github.com/Aryan132005",
        "followers_url": "https://api.github.com/users/Aryan132005/followers",
        "following_url": "https://api.github.com/users/Aryan132005/following{/other_user}",
        "gists_url": "https://api.github.com/users/Aryan132005/gists{/gist_id}",
        "starred_url": "https://api.github.com/users/Aryan132005/starred{/owner}{/repo}",
        "subscriptions_url": "https://api.github.com/users/Aryan132005/subscriptions",
        "organizations_url": "https://api.github.com/users/Aryan132005/orgs",
        "repos_url": "https://api.github.com/users/Aryan132005/repos",
        "events_url": "https://api.github.com/users/Aryan132005/events{/privacy}",
        "received_events_url": "https://api.github.com/users/Aryan132005/received_events",
        "type": "User",
        "user_view_type": "public",
        "site_admin": false
      },
      "jobs_url": "https://api.github.com/repos/Aryan132005/Steller-Yellowbelt/actions/runs/28773350443/jobs",
      "logs_url": "https://api.github.com/repos/Aryan132005/Steller-Yellowbelt/actions/runs/28773350443/logs",
      "check_suite_url": "https://api.github.com/repos/Aryan132005/Steller-Yellowbelt/check-suites/77759318560",
      "artifacts_url": "https://api.github.com/repos/Aryan132005/Steller-Yellowbelt/actions/runs/28773350443/artifacts",
      "cancel_url": "https://api.github.com/repos/Aryan132005/Steller-Yellowbelt/actions/runs/28773350443/cancel",
      "rerun_url": "https://api.github.com/repos/Aryan132005/Steller-Yellowbelt/actions/runs/28773350443/rerun",
      "previous_attempt_url": null,
      "workflow_url": "https://api.github.com/repos/Aryan132005/Steller-Yellowbelt/actions/workflows/307823677",
      "head_commit": {
        "id": "f59a32a6758c900150b3309050c3083664faeef7",
        "tree_id": "149e17eefe885442401c3f1ba19a08c0212fc0f9",
        "message": "Fix CI toolchain action version",
        "timestamp": "2026-07-06T06:50:56Z",
        "author": {
          "name": "Aryan Saini",
          "email": "aryansaini132005@gmail.com"
        },
        "committer": {
          "name": "Aryan Saini",
          "email": "aryansaini132005@gmail.com"
        }
      },
      "repository": {
        "id": 1290657800,
        "node_id": "R_kgDOTO3gCA",
        "name": "Steller-Yellowbelt",
        "full_name": "Aryan132005/Steller-Yellowbelt",
        "private": false,
        "owner": {
          "login": "Aryan132005",
          "id": 146818102,
          "node_id": "U_kgDOCMBENg",
          "avatar_url": "https://avatars.githubusercontent.com/u/146818102?v=4",
          "gravatar_id": "",
          "url": "https://api.github.com/users/Aryan132005",
          "html_url": "https://github.com/Aryan132005",
          "followers_url": "https://api.github.com/users/Aryan132005/followers",
          "following_url": "https://api.github.com/users/Aryan132005/following{/other_user}",
          "gists_url": "https://api.github.com/users/Aryan132005/gists{/gist_id}",
          "starred_url": "https://api.github.com/users/Aryan132005/starred{/owner}{/repo}",
          "subscriptions_url": "https://api.github.com/users/Aryan132005/subscriptions",
          "organizations_url": "https://api.github.com/users/Aryan132005/orgs",
          "repos_url": "https://api.github.com/users/Aryan132005/repos",
          "events_url": "https://api.github.com/users/Aryan132005/events{/privacy}",
          "received_events_url": "https://api.github.com/users/Aryan132005/received_events",
          "type": "User",
          "user_view_type": "public",
          "site_admin": false
        },
        "html_url": "https://github.com/Aryan132005/Steller-Yellowbelt",
        "description": null,
        "fork": false,
        "url": "https://api.github.com/repos/Aryan132005/Steller-Yellowbelt",
        "forks_url": "https://api.github.com/repos/Aryan132005/Steller-Yellowbelt/forks",
        "keys_url": "https://api.github.com/repos/Aryan132005/Steller-Yellowbelt/keys{/key_id}",
        "collaborators_url": "https://api.github.com/repos/Aryan132005/Steller-Yellowbelt/collaborators{/collaborator}",
        "teams_url": "https://api.github.com/repos/Aryan132005/Steller-Yellowbelt/teams",
        "hooks_url": "https://api.github.com/repos/Aryan132005/Steller-Yellowbelt/hooks",
        "issue_events_url": "https://api.github.com/repos/Aryan132005/Steller-Yellowbelt/issues/events{/number}",
        "events_url": "https://api.github.com/repos/Aryan132005/Steller-Yellowbelt/events",
        "assignees_url": "https://api.github.com/repos/Aryan132005/Steller-Yellowbelt/assignees{/user}",
        "branches_url": "https://api.github.com/repos/Aryan132005/Steller-Yellowbelt/branches{/branch}",
        "tags_url": "https://api.github.com/repos/Aryan132005/Steller-Yellowbelt/tags",
        "blobs_url": "https://api.github.com/repos/Aryan132005/Steller-Yellowbelt/git/blobs{/sha}",
        "git_tags_url": "https://api.github.com/repos/Aryan132005/Steller-Yellowbelt/git/tags{/sha}",
        "git_refs_url": "https://api.github.com/repos/Aryan132005/Steller-Yellowbelt/git/refs{/sha}",
        "trees_url": "https://api.github.com/repos/Aryan132005/Steller-Yellowbelt/git/trees{/sha}",
        "statuses_url": "https://api.github.com/repos/Aryan132005/Steller-Yellowbelt/statuses/{sha}",
        "languages_url": "https://api.github.com/repos/Aryan132005/Steller-Yellowbelt/languages",
        "stargazers_url": "https://api.github.com/repos/Aryan132005/Steller-Yellowbelt/stargazers",
        "contributors_url": "https://api.github.com/repos/Aryan132005/Steller-Yellowbelt/contributors",
        "subscribers_url": "https://api.github.com/repos/Aryan132005/Steller-Yellowbelt/subscribers",
        "subscription_url": "https://api.github.com/repos/Aryan132005/Steller-Yellowbelt/subscription",
        "commits_url": "https://api.github.com/repos/Aryan132005/Steller-Yellowbelt/commits{/sha}",
        "git_commits_url": "https://api.github.com/repos/Aryan132005/Steller-Yellowbelt/git/commits{/sha}",
        "comments_url": "https://api.github.com/repos/Aryan132005/Steller-Yellowbelt/comments{/number}",
        "issue_comment_url": "https://api.github.com/repos/Aryan132005/Steller-Yellowbelt/issues/comments{/number}",
        "contents_url": "https://api.github.com/repos/Aryan132005/Steller-Yellowbelt/contents/{+path}",
        "compare_url": "https://api.github.com/repos/Aryan132005/Steller-Yellowbelt/compare/{base}...{head}",
        "merges_url": "https://api.github.com/repos/Aryan132005/Steller-Yellowbelt/merges",
        "archive_url": "https://api.github.com/repos/Aryan132005/Steller-Yellowbelt/{archive_format}{/ref}",
        "downloads_url": "https://api.github.com/repos/Aryan132005/Steller-Yellowbelt/downloads",
        "issues_url": "https://api.github.com/repos/Aryan132005/Steller-Yellowbelt/issues{/number}",
        "pulls_url": "https://api.github.com/repos/Aryan132005/Steller-Yellowbelt/pulls{/number}",
        "milestones_url": "https://api.github.com/repos/Aryan132005/Steller-Yellowbelt/milestones{/number}",
        "notifications_url": "https://api.github.com/repos/Aryan132005/Steller-Yellowbelt/notifications{?since,all,participating}",
        "labels_url": "https://api.github.com/repos/Aryan132005/Steller-Yellowbelt/labels{/name}",
        "releases_url": "https://api.github.com/repos/Aryan132005/Steller-Yellowbelt/releases{/id}",
        "deployments_url": "https://api.github.com/repos/Aryan132005/Steller-Yellowbelt/deployments"
      },
      "head_repository": {
        "id": 1290657800,
        "node_id": "R_kgDOTO3gCA",
        "name": "Steller-Yellowbelt",
        "full_name": "Aryan132005/Steller-Yellowbelt",
        "private": false,
        "owner": {
          "login": "Aryan132005",
          "id": 146818102,
          "node_id": "U_kgDOCMBENg",
          "avatar_url": "https://avatars.githubusercontent.com/u/146818102?v=4",
          "gravatar_id": "",
          "url": "https://api.github.com/users/Aryan132005",
          "html_url": "https://github.com/Aryan132005",
          "followers_url": "https://api.github.com/users/Aryan132005/followers",
          "following_url": "https://api.github.com/users/Aryan132005/following{/other_user}",
          "gists_url": "https://api.github.com/users/Aryan132005/gists{/gist_id}",
          "starred_url": "https://api.github.com/users/Aryan132005/starred{/owner}{/repo}",
          "subscriptions_url": "https://api.github.com/users/Aryan132005/subscriptions",
          "organizations_url": "https://api.github.com/users/Aryan132005/orgs",
          "repos_url": "https://api.github.com/users/Aryan132005/repos",
          "events_url": "https://api.github.com/users/Aryan132005/events{/privacy}",
          "received_events_url": "https://api.github.com/users/Aryan132005/received_events",
          "type": "User",
          "user_view_type": "public",
          "site_admin": false
        },
        "html_url": "https://github.com/Aryan132005/Steller-Yellowbelt",
        "description": null,
        "fork": false,
        "url": "https://api.github.com/repos/Aryan132005/Steller-Yellowbelt",
        "forks_url": "https://api.github.com/repos/Aryan132005/Steller-Yellowbelt/forks",
        "keys_url": "https://api.github.com/repos/Aryan132005/Steller-Yellowbelt/keys{/key_id}",
        "collaborators_url": "https://api.github.com/repos/Aryan132005/Steller-Yellowbelt/collaborators{/collaborator}",
        "teams_url": "https://api.github.com/repos/Aryan132005/Steller-Yellowbelt/teams",
        "hooks_url": "https://api.github.com/repos/Aryan132005/Steller-Yellowbelt/hooks",
        "issue_events_url": "https://api.github.com/repos/Aryan132005/Steller-Yellowbelt/issues/events{/number}",
        "events_url": "https://api.github.com/repos/Aryan132005/Steller-Yellowbelt/events",
        "assignees_url": "https://api.github.com/repos/Aryan132005/Steller-Yellowbelt/assignees{/user}",
        "branches_url": "https://api.github.com/repos/Aryan132005/Steller-Yellowbelt/branches{/branch}",
        "tags_url": "https://api.github.com/repos/Aryan132005/Steller-Yellowbelt/tags",
        "blobs_url": "https://api.github.com/repos/Aryan132005/Steller-Yellowbelt/git/blobs{/sha}",
        "git_tags_url": "https://api.github.com/repos/Aryan132005/Steller-Yellowbelt/git/tags{/sha}",
        "git_refs_url": "https://api.github.com/repos/Aryan132005/Steller-Yellowbelt/git/refs{/sha}",
        "trees_url": "https://api.github.com/repos/Aryan132005/Steller-Yellowbelt/git/trees{/sha}",
        "statuses_url": "https://api.github.com/repos/Aryan132005/Steller-Yellowbelt/statuses/{sha}",
        "languages_url": "https://api.github.com/repos/Aryan132005/Steller-Yellowbelt/languages",
        "stargazers_url": "https://api.github.com/repos/Aryan132005/Steller-Yellowbelt/stargazers",
        "contributors_url": "https://api.github.com/repos/Aryan132005/Steller-Yellowbelt/contributors",
        "subscribers_url": "https://api.github.com/repos/Aryan132005/Steller-Yellowbelt/subscribers",
        "subscription_url": "https://api.github.com/repos/Aryan132005/Steller-Yellowbelt/subscription",
        "commits_url": "https://api.github.com/repos/Aryan132005/Steller-Yellowbelt/commits{/sha}",
        "git_commits_url": "https://api.github.com/repos/Aryan132005/Steller-Yellowbelt/git/commits{/sha}",
        "comments_url": "https://api.github.com/repos/Aryan132005/Steller-Yellowbelt/comments{/number}",
        "issue_comment_url": "https://api.github.com/repos/Aryan132005/Steller-Yellowbelt/issues/comments{/number}",
        "contents_url": "https://api.github.com/repos/Aryan132005/Steller-Yellowbelt/contents/{+path}",
        "compare_url": "https://api.github.com/repos/Aryan132005/Steller-Yellowbelt/compare/{base}...{head}",
        "merges_url": "https://api.github.com/repos/Aryan132005/Steller-Yellowbelt/merges",
        "archive_url": "https://api.github.com/repos/Aryan132005/Steller-Yellowbelt/{archive_format}{/ref}",
        "downloads_url": "https://api.github.com/repos/Aryan132005/Steller-Yellowbelt/downloads",
        "issues_url": "https://api.github.com/repos/Aryan132005/Steller-Yellowbelt/issues{/number}",
        "pulls_url": "https://api.github.com/repos/Aryan132005/Steller-Yellowbelt/pulls{/number}",
        "milestones_url": "https://api.github.com/repos/Aryan132005/Steller-Yellowbelt/milestones{/number}",
        "notifications_url": "https://api.github.com/repos/Aryan132005/Steller-Yellowbelt/notifications{?since,all,participating}",
        "labels_url": "https://api.github.com/repos/Aryan132005/Steller-Yellowbelt/labels{/name}",
        "releases_url": "https://api.github.com/repos/Aryan132005/Steller-Yellowbelt/releases{/id}",
        "deployments_url": "https://api.github.com/repos/Aryan132005/Steller-Yellowbelt/deployments"
      }
    },
    {
      "id": 28773194238,
      "name": "Deploy Frontend",
      "node_id": "WFR_kwLOTO3gCM8AAAAGswQZ_g",
      "head_branch": "main",
      "head_sha": "268ffde1e57007a765d03937f37cb4afbfe63cba",
      "path": ".github/workflows/deploy.yml",
      "display_title": "Initial commit with contracts and workflows",
      "run_number": 1,
      "event": "push",
      "status": "completed",
      "conclusion": "skipped",
      "workflow_id": 307823681,
      "check_suite_id": 77758871572,
      "check_suite_node_id": "CS_kwDOTO3gCM8AAAASGso4FA",
      "url": "https://api.github.com/repos/Aryan132005/Steller-Yellowbelt/actions/runs/28773194238",
      "html_url": "https://github.com/Aryan132005/Steller-Yellowbelt/actions/runs/28773194238",
      "pull_requests": [

      ],
      "created_at": "2026-07-06T06:47:25Z",
      "updated_at": "2026-07-06T06:47:25Z",
      "actor": {
        "login": "Aryan132005",
        "id": 146818102,
        "node_id": "U_kgDOCMBENg",
        "avatar_url": "https://avatars.githubusercontent.com/u/146818102?v=4",
        "gravatar_id": "",
        "url": "https://api.github.com/users/Aryan132005",
        "html_url": "https://github.com/Aryan132005",
        "followers_url": "https://api.github.com/users/Aryan132005/followers",
        "following_url": "https://api.github.com/users/Aryan132005/following{/other_user}",
        "gists_url": "https://api.github.com/users/Aryan132005/gists{/gist_id}",
        "starred_url": "https://api.github.com/users/Aryan132005/starred{/owner}{/repo}",
        "subscriptions_url": "https://api.github.com/users/Aryan132005/subscriptions",
        "organizations_url": "https://api.github.com/users/Aryan132005/orgs",
        "repos_url": "https://api.github.com/users/Aryan132005/repos",
        "events_url": "https://api.github.com/users/Aryan132005/events{/privacy}",
        "received_events_url": "https://api.github.com/users/Aryan132005/received_events",
        "type": "User",
        "user_view_type": "public",
        "site_admin": false
      },
      "run_attempt": 1,
      "referenced_workflows": [

      ],
      "run_started_at": "2026-07-06T06:47:25Z",
      "triggering_actor": {
        "login": "Aryan132005",
        "id": 146818102,
        "node_id": "U_kgDOCMBENg",
        "avatar_url": "https://avatars.githubusercontent.com/u/146818102?v=4",
        "gravatar_id": "",
        "url": "https://api.github.com/users/Aryan132005",
        "html_url": "https://github.com/Aryan132005",
        "followers_url": "https://api.github.com/users/Aryan132005/followers",
        "following_url": "https://api.github.com/users/Aryan132005/following{/other_user}",
        "gists_url": "https://api.github.com/users/Aryan132005/gists{/gist_id}",
        "starred_url": "https://api.github.com/users/Aryan132005/starred{/owner}{/repo}",
        "subscriptions_url": "https://api.github.com/users/Aryan132005/subscriptions",
        "organizations_url": "https://api.github.com/users/Aryan132005/orgs",
        "repos_url": "https://api.github.com/users/Aryan132005/repos",
        "events_url": "https://api.github.com/users/Aryan132005/events{/privacy}",
        "received_events_url": "https://api.github.com/users/Aryan132005/received_events",
        "type": "User",
        "user_view_type": "public",
        "site_admin": false
      },
      "jobs_url": "https://api.github.com/repos/Aryan132005/Steller-Yellowbelt/actions/runs/28773194238/jobs",
      "logs_url": "https://api.github.com/repos/Aryan132005/Steller-Yellowbelt/actions/runs/28773194238/logs",
      "check_suite_url": "https://api.github.com/repos/Aryan132005/Steller-Yellowbelt/check-suites/77758871572",
      "artifacts_url": "https://api.github.com/repos/Aryan132005/Steller-Yellowbelt/actions/runs/28773194238/artifacts",
      "cancel_url": "https://api.github.com/repos/Aryan132005/Steller-Yellowbelt/actions/runs/28773194238/cancel",
      "rerun_url": "https://api.github.com/repos/Aryan132005/Steller-Yellowbelt/actions/runs/28773194238/rerun",
      "previous_attempt_url": null,
      "workflow_url": "https://api.github.com/repos/Aryan132005/Steller-Yellowbelt/actions/workflows/307823681",
      "head_commit": {
        "id": "268ffde1e57007a765d03937f37cb4afbfe63cba",
        "tree_id": "75602f383dd3532008d003d0897803afe0a0eefd",
        "message": "Initial commit with contracts and workflows",
        "timestamp": "2026-07-06T06:47:07Z",
        "author": {
          "name": "Aryan Saini",
          "email": "aryansaini132005@gmail.com"
        },
        "committer": {
          "name": "Aryan Saini",
          "email": "aryansaini132005@gmail.com"
        }
      },
      "repository": {
        "id": 1290657800,
        "node_id": "R_kgDOTO3gCA",
        "name": "Steller-Yellowbelt",
        "full_name": "Aryan132005/Steller-Yellowbelt",
        "private": false,
        "owner": {
          "login": "Aryan132005",
          "id": 146818102,
          "node_id": "U_kgDOCMBENg",
          "avatar_url": "https://avatars.githubusercontent.com/u/146818102?v=4",
          "gravatar_id": "",
          "url": "https://api.github.com/users/Aryan132005",
          "html_url": "https://github.com/Aryan132005",
          "followers_url": "https://api.github.com/users/Aryan132005/followers",
          "following_url": "https://api.github.com/users/Aryan132005/following{/other_user}",
          "gists_url": "https://api.github.com/users/Aryan132005/gists{/gist_id}",
          "starred_url": "https://api.github.com/users/Aryan132005/starred{/owner}{/repo}",
          "subscriptions_url": "https://api.github.com/users/Aryan132005/subscriptions",
          "organizations_url": "https://api.github.com/users/Aryan132005/orgs",
          "repos_url": "https://api.github.com/users/Aryan132005/repos",
          "events_url": "https://api.github.com/users/Aryan132005/events{/privacy}",
          "received_events_url": "https://api.github.com/users/Aryan132005/received_events",
          "type": "User",
          "user_view_type": "public",
          "site_admin": false
        },
        "html_url": "https://github.com/Aryan132005/Steller-Yellowbelt",
        "description": null,
        "fork": false,
        "url": "https://api.github.com/repos/Aryan132005/Steller-Yellowbelt",
        "forks_url": "https://api.github.com/repos/Aryan132005/Steller-Yellowbelt/forks",
        "keys_url": "https://api.github.com/repos/Aryan132005/Steller-Yellowbelt/keys{/key_id}",
        "collaborators_url": "https://api.github.com/repos/Aryan132005/Steller-Yellowbelt/collaborators{/collaborator}",
        "teams_url": "https://api.github.com/repos/Aryan132005/Steller-Yellowbelt/teams",
        "hooks_url": "https://api.github.com/repos/Aryan132005/Steller-Yellowbelt/hooks",
        "issue_events_url": "https://api.github.com/repos/Aryan132005/Steller-Yellowbelt/issues/events{/number}",
        "events_url": "https://api.github.com/repos/Aryan132005/Steller-Yellowbelt/events",
        "assignees_url": "https://api.github.com/repos/Aryan132005/Steller-Yellowbelt/assignees{/user}",
        "branches_url": "https://api.github.com/repos/Aryan132005/Steller-Yellowbelt/branches{/branch}",
        "tags_url": "https://api.github.com/repos/Aryan132005/Steller-Yellowbelt/tags",
        "blobs_url": "https://api.github.com/repos/Aryan132005/Steller-Yellowbelt/git/blobs{/sha}",
        "git_tags_url": "https://api.github.com/repos/Aryan132005/Steller-Yellowbelt/git/tags{/sha}",
        "git_refs_url": "https://api.github.com/repos/Aryan132005/Steller-Yellowbelt/git/refs{/sha}",
        "trees_url": "https://api.github.com/repos/Aryan132005/Steller-Yellowbelt/git/trees{/sha}",
        "statuses_url": "https://api.github.com/repos/Aryan132005/Steller-Yellowbelt/statuses/{sha}",
        "languages_url": "https://api.github.com/repos/Aryan132005/Steller-Yellowbelt/languages",
        "stargazers_url": "https://api.github.com/repos/Aryan132005/Steller-Yellowbelt/stargazers",
        "contributors_url": "https://api.github.com/repos/Aryan132005/Steller-Yellowbelt/contributors",
        "subscribers_url": "https://api.github.com/repos/Aryan132005/Steller-Yellowbelt/subscribers",
        "subscription_url": "https://api.github.com/repos/Aryan132005/Steller-Yellowbelt/subscription",
        "commits_url": "https://api.github.com/repos/Aryan132005/Steller-Yellowbelt/commits{/sha}",
        "git_commits_url": "https://api.github.com/repos/Aryan132005/Steller-Yellowbelt/git/commits{/sha}",
        "comments_url": "https://api.github.com/repos/Aryan132005/Steller-Yellowbelt/comments{/number}",
        "issue_comment_url": "https://api.github.com/repos/Aryan132005/Steller-Yellowbelt/issues/comments{/number}",
        "contents_url": "https://api.github.com/repos/Aryan132005/Steller-Yellowbelt/contents/{+path}",
        "compare_url": "https://api.github.com/repos/Aryan132005/Steller-Yellowbelt/compare/{base}...{head}",
        "merges_url": "https://api.github.com/repos/Aryan132005/Steller-Yellowbelt/merges",
        "archive_url": "https://api.github.com/repos/Aryan132005/Steller-Yellowbelt/{archive_format}{/ref}",
        "downloads_url": "https://api.github.com/repos/Aryan132005/Steller-Yellowbelt/downloads",
        "issues_url": "https://api.github.com/repos/Aryan132005/Steller-Yellowbelt/issues{/number}",
        "pulls_url": "https://api.github.com/repos/Aryan132005/Steller-Yellowbelt/pulls{/number}",
        "milestones_url": "https://api.github.com/repos/Aryan132005/Steller-Yellowbelt/milestones{/number}",
        "notifications_url": "https://api.github.com/repos/Aryan132005/Steller-Yellowbelt/notifications{?since,all,participating}",
        "labels_url": "https://api.github.com/repos/Aryan132005/Steller-Yellowbelt/labels{/name}",
        "releases_url": "https://api.github.com/repos/Aryan132005/Steller-Yellowbelt/releases{/id}",
        "deployments_url": "https://api.github.com/repos/Aryan132005/Steller-Yellowbelt/deployments"
      },
      "head_repository": {
        "id": 1290657800,
        "node_id": "R_kgDOTO3gCA",
        "name": "Steller-Yellowbelt",
        "full_name": "Aryan132005/Steller-Yellowbelt",
        "private": false,
        "owner": {
          "login": "Aryan132005",
          "id": 146818102,
          "node_id": "U_kgDOCMBENg",
          "avatar_url": "https://avatars.githubusercontent.com/u/146818102?v=4",
          "gravatar_id": "",
          "url": "https://api.github.com/users/Aryan132005",
          "html_url": "https://github.com/Aryan132005",
          "followers_url": "https://api.github.com/users/Aryan132005/followers",
          "following_url": "https://api.github.com/users/Aryan132005/following{/other_user}",
          "gists_url": "https://api.github.com/users/Aryan132005/gists{/gist_id}",
          "starred_url": "https://api.github.com/users/Aryan132005/starred{/owner}{/repo}",
          "subscriptions_url": "https://api.github.com/users/Aryan132005/subscriptions",
          "organizations_url": "https://api.github.com/users/Aryan132005/orgs",
          "repos_url": "https://api.github.com/users/Aryan132005/repos",
          "events_url": "https://api.github.com/users/Aryan132005/events{/privacy}",
          "received_events_url": "https://api.github.com/users/Aryan132005/received_events",
          "type": "User",
          "user_view_type": "public",
          "site_admin": false
        },
        "html_url": "https://github.com/Aryan132005/Steller-Yellowbelt",
        "description": null,
        "fork": false,
        "url": "https://api.github.com/repos/Aryan132005/Steller-Yellowbelt",
        "forks_url": "https://api.github.com/repos/Aryan132005/Steller-Yellowbelt/forks",
        "keys_url": "https://api.github.com/repos/Aryan132005/Steller-Yellowbelt/keys{/key_id}",
        "collaborators_url": "https://api.github.com/repos/Aryan132005/Steller-Yellowbelt/collaborators{/collaborator}",
        "teams_url": "https://api.github.com/repos/Aryan132005/Steller-Yellowbelt/teams",
        "hooks_url": "https://api.github.com/repos/Aryan132005/Steller-Yellowbelt/hooks",
        "issue_events_url": "https://api.github.com/repos/Aryan132005/Steller-Yellowbelt/issues/events{/number}",
        "events_url": "https://api.github.com/repos/Aryan132005/Steller-Yellowbelt/events",
        "assignees_url": "https://api.github.com/repos/Aryan132005/Steller-Yellowbelt/assignees{/user}",
        "branches_url": "https://api.github.com/repos/Aryan132005/Steller-Yellowbelt/branches{/branch}",
        "tags_url": "https://api.github.com/repos/Aryan132005/Steller-Yellowbelt/tags",
        "blobs_url": "https://api.github.com/repos/Aryan132005/Steller-Yellowbelt/git/blobs{/sha}",
        "git_tags_url": "https://api.github.com/repos/Aryan132005/Steller-Yellowbelt/git/tags{/sha}",
        "git_refs_url": "https://api.github.com/repos/Aryan132005/Steller-Yellowbelt/git/refs{/sha}",
        "trees_url": "https://api.github.com/repos/Aryan132005/Steller-Yellowbelt/git/trees{/sha}",
        "statuses_url": "https://api.github.com/repos/Aryan132005/Steller-Yellowbelt/statuses/{sha}",
        "languages_url": "https://api.github.com/repos/Aryan132005/Steller-Yellowbelt/languages",
        "stargazers_url": "https://api.github.com/repos/Aryan132005/Steller-Yellowbelt/stargazers",
        "contributors_url": "https://api.github.com/repos/Aryan132005/Steller-Yellowbelt/contributors",
        "subscribers_url": "https://api.github.com/repos/Aryan132005/Steller-Yellowbelt/subscribers",
        "subscription_url": "https://api.github.com/repos/Aryan132005/Steller-Yellowbelt/subscription",
        "commits_url": "https://api.github.com/repos/Aryan132005/Steller-Yellowbelt/commits{/sha}",
        "git_commits_url": "https://api.github.com/repos/Aryan132005/Steller-Yellowbelt/git/commits{/sha}",
        "comments_url": "https://api.github.com/repos/Aryan132005/Steller-Yellowbelt/comments{/number}",
        "issue_comment_url": "https://api.github.com/repos/Aryan132005/Steller-Yellowbelt/issues/comments{/number}",
        "contents_url": "https://api.github.com/repos/Aryan132005/Steller-Yellowbelt/contents/{+path}",
        "compare_url": "https://api.github.com/repos/Aryan132005/Steller-Yellowbelt/compare/{base}...{head}",
        "merges_url": "https://api.github.com/repos/Aryan132005/Steller-Yellowbelt/merges",
        "archive_url": "https://api.github.com/repos/Aryan132005/Steller-Yellowbelt/{archive_format}{/ref}",
        "downloads_url": "https://api.github.com/repos/Aryan132005/Steller-Yellowbelt/downloads",
        "issues_url": "https://api.github.com/repos/Aryan132005/Steller-Yellowbelt/issues{/number}",
        "pulls_url": "https://api.github.com/repos/Aryan132005/Steller-Yellowbelt/pulls{/number}",
        "milestones_url": "https://api.github.com/repos/Aryan132005/Steller-Yellowbelt/milestones{/number}",
        "notifications_url": "https://api.github.com/repos/Aryan132005/Steller-Yellowbelt/notifications{?since,all,participating}",
        "labels_url": "https://api.github.com/repos/Aryan132005/Steller-Yellowbelt/labels{/name}",
        "releases_url": "https://api.github.com/repos/Aryan132005/Steller-Yellowbelt/releases{/id}",
        "deployments_url": "https://api.github.com/repos/Aryan132005/Steller-Yellowbelt/deployments"
      }
    },
    {
      "id": 28773194232,
      "name": "CI",
      "node_id": "WFR_kwLOTO3gCM8AAAAGswQZ-A",
      "head_branch": "main",
      "head_sha": "268ffde1e57007a765d03937f37cb4afbfe63cba",
      "path": ".github/workflows/ci.yml",
      "display_title": "Initial commit with contracts and workflows",
      "run_number": 1,
      "event": "push",
      "status": "completed",
      "conclusion": "failure",
      "workflow_id": 307823677,
      "check_suite_id": 77758871567,
      "check_suite_node_id": "CS_kwDOTO3gCM8AAAASGso4Dw",
      "url": "https://api.github.com/repos/Aryan132005/Steller-Yellowbelt/actions/runs/28773194232",
      "html_url": "https://github.com/Aryan132005/Steller-Yellowbelt/actions/runs/28773194232",
      "pull_requests": [

      ],
      "created_at": "2026-07-06T06:47:25Z",
      "updated_at": "2026-07-06T06:48:18Z",
      "actor": {
        "login": "Aryan132005",
        "id": 146818102,
        "node_id": "U_kgDOCMBENg",
        "avatar_url": "https://avatars.githubusercontent.com/u/146818102?v=4",
        "gravatar_id": "",
        "url": "https://api.github.com/users/Aryan132005",
        "html_url": "https://github.com/Aryan132005",
        "followers_url": "https://api.github.com/users/Aryan132005/followers",
        "following_url": "https://api.github.com/users/Aryan132005/following{/other_user}",
        "gists_url": "https://api.github.com/users/Aryan132005/gists{/gist_id}",
        "starred_url": "https://api.github.com/users/Aryan132005/starred{/owner}{/repo}",
        "subscriptions_url": "https://api.github.com/users/Aryan132005/subscriptions",
        "organizations_url": "https://api.github.com/users/Aryan132005/orgs",
        "repos_url": "https://api.github.com/users/Aryan132005/repos",
        "events_url": "https://api.github.com/users/Aryan132005/events{/privacy}",
        "received_events_url": "https://api.github.com/users/Aryan132005/received_events",
        "type": "User",
        "user_view_type": "public",
        "site_admin": false
      },
      "run_attempt": 1,
      "referenced_workflows": [

      ],
      "run_started_at": "2026-07-06T06:47:25Z",
      "triggering_actor": {
        "login": "Aryan132005",
        "id": 146818102,
        "node_id": "U_kgDOCMBENg",
        "avatar_url": "https://avatars.githubusercontent.com/u/146818102?v=4",
        "gravatar_id": "",
        "url": "https://api.github.com/users/Aryan132005",
        "html_url": "https://github.com/Aryan132005",
        "followers_url": "https://api.github.com/users/Aryan132005/followers",
        "following_url": "https://api.github.com/users/Aryan132005/following{/other_user}",
        "gists_url": "https://api.github.com/users/Aryan132005/gists{/gist_id}",
        "starred_url": "https://api.github.com/users/Aryan132005/starred{/owner}{/repo}",
        "subscriptions_url": "https://api.github.com/users/Aryan132005/subscriptions",
        "organizations_url": "https://api.github.com/users/Aryan132005/orgs",
        "repos_url": "https://api.github.com/users/Aryan132005/repos",
        "events_url": "https://api.github.com/users/Aryan132005/events{/privacy}",
        "received_events_url": "https://api.github.com/users/Aryan132005/received_events",
        "type": "User",
        "user_view_type": "public",
        "site_admin": false
      },
      "jobs_url": "https://api.github.com/repos/Aryan132005/Steller-Yellowbelt/actions/runs/28773194232/jobs",
      "logs_url": "https://api.github.com/repos/Aryan132005/Steller-Yellowbelt/actions/runs/28773194232/logs",
      "check_suite_url": "https://api.github.com/repos/Aryan132005/Steller-Yellowbelt/check-suites/77758871567",
      "artifacts_url": "https://api.github.com/repos/Aryan132005/Steller-Yellowbelt/actions/runs/28773194232/artifacts",
      "cancel_url": "https://api.github.com/repos/Aryan132005/Steller-Yellowbelt/actions/runs/28773194232/cancel",
      "rerun_url": "https://api.github.com/repos/Aryan132005/Steller-Yellowbelt/actions/runs/28773194232/rerun",
      "previous_attempt_url": null,
      "workflow_url": "https://api.github.com/repos/Aryan132005/Steller-Yellowbelt/actions/workflows/307823677",
      "head_commit": {
        "id": "268ffde1e57007a765d03937f37cb4afbfe63cba",
        "tree_id": "75602f383dd3532008d003d0897803afe0a0eefd",
        "message": "Initial commit with contracts and workflows",
        "timestamp": "2026-07-06T06:47:07Z",
        "author": {
          "name": "Aryan Saini",
          "email": "aryansaini132005@gmail.com"
        },
        "committer": {
          "name": "Aryan Saini",
          "email": "aryansaini132005@gmail.com"
        }
      },
      "repository": {
        "id": 1290657800,
        "node_id": "R_kgDOTO3gCA",
        "name": "Steller-Yellowbelt",
        "full_name": "Aryan132005/Steller-Yellowbelt",
        "private": false,
        "owner": {
          "login": "Aryan132005",
          "id": 146818102,
          "node_id": "U_kgDOCMBENg",
          "avatar_url": "https://avatars.githubusercontent.com/u/146818102?v=4",
          "gravatar_id": "",
          "url": "https://api.github.com/users/Aryan132005",
          "html_url": "https://github.com/Aryan132005",
          "followers_url": "https://api.github.com/users/Aryan132005/followers",
          "following_url": "https://api.github.com/users/Aryan132005/following{/other_user}",
          "gists_url": "https://api.github.com/users/Aryan132005/gists{/gist_id}",
          "starred_url": "https://api.github.com/users/Aryan132005/starred{/owner}{/repo}",
          "subscriptions_url": "https://api.github.com/users/Aryan132005/subscriptions",
          "organizations_url": "https://api.github.com/users/Aryan132005/orgs",
          "repos_url": "https://api.github.com/users/Aryan132005/repos",
          "events_url": "https://api.github.com/users/Aryan132005/events{/privacy}",
          "received_events_url": "https://api.github.com/users/Aryan132005/received_events",
          "type": "User",
          "user_view_type": "public",
          "site_admin": false
        },
        "html_url": "https://github.com/Aryan132005/Steller-Yellowbelt",
        "description": null,
        "fork": false,
        "url": "https://api.github.com/repos/Aryan132005/Steller-Yellowbelt",
        "forks_url": "https://api.github.com/repos/Aryan132005/Steller-Yellowbelt/forks",
        "keys_url": "https://api.github.com/repos/Aryan132005/Steller-Yellowbelt/keys{/key_id}",
        "collaborators_url": "https://api.github.com/repos/Aryan132005/Steller-Yellowbelt/collaborators{/collaborator}",
        "teams_url": "https://api.github.com/repos/Aryan132005/Steller-Yellowbelt/teams",
        "hooks_url": "https://api.github.com/repos/Aryan132005/Steller-Yellowbelt/hooks",
        "issue_events_url": "https://api.github.com/repos/Aryan132005/Steller-Yellowbelt/issues/events{/number}",
        "events_url": "https://api.github.com/repos/Aryan132005/Steller-Yellowbelt/events",
        "assignees_url": "https://api.github.com/repos/Aryan132005/Steller-Yellowbelt/assignees{/user}",
        "branches_url": "https://api.github.com/repos/Aryan132005/Steller-Yellowbelt/branches{/branch}",
        "tags_url": "https://api.github.com/repos/Aryan132005/Steller-Yellowbelt/tags",
        "blobs_url": "https://api.github.com/repos/Aryan132005/Steller-Yellowbelt/git/blobs{/sha}",
        "git_tags_url": "https://api.github.com/repos/Aryan132005/Steller-Yellowbelt/git/tags{/sha}",
        "git_refs_url": "https://api.github.com/repos/Aryan132005/Steller-Yellowbelt/git/refs{/sha}",
        "trees_url": "https://api.github.com/repos/Aryan132005/Steller-Yellowbelt/git/trees{/sha}",
        "statuses_url": "https://api.github.com/repos/Aryan132005/Steller-Yellowbelt/statuses/{sha}",
        "languages_url": "https://api.github.com/repos/Aryan132005/Steller-Yellowbelt/languages",
        "stargazers_url": "https://api.github.com/repos/Aryan132005/Steller-Yellowbelt/stargazers",
        "contributors_url": "https://api.github.com/repos/Aryan132005/Steller-Yellowbelt/contributors",
        "subscribers_url": "https://api.github.com/repos/Aryan132005/Steller-Yellowbelt/subscribers",
        "subscription_url": "https://api.github.com/repos/Aryan132005/Steller-Yellowbelt/subscription",
        "commits_url": "https://api.github.com/repos/Aryan132005/Steller-Yellowbelt/commits{/sha}",
        "git_commits_url": "https://api.github.com/repos/Aryan132005/Steller-Yellowbelt/git/commits{/sha}",
        "comments_url": "https://api.github.com/repos/Aryan132005/Steller-Yellowbelt/comments{/number}",
        "issue_comment_url": "https://api.github.com/repos/Aryan132005/Steller-Yellowbelt/issues/comments{/number}",
        "contents_url": "https://api.github.com/repos/Aryan132005/Steller-Yellowbelt/contents/{+path}",
        "compare_url": "https://api.github.com/repos/Aryan132005/Steller-Yellowbelt/compare/{base}...{head}",
        "merges_url": "https://api.github.com/repos/Aryan132005/Steller-Yellowbelt/merges",
        "archive_url": "https://api.github.com/repos/Aryan132005/Steller-Yellowbelt/{archive_format}{/ref}",
        "downloads_url": "https://api.github.com/repos/Aryan132005/Steller-Yellowbelt/downloads",
        "issues_url": "https://api.github.com/repos/Aryan132005/Steller-Yellowbelt/issues{/number}",
        "pulls_url": "https://api.github.com/repos/Aryan132005/Steller-Yellowbelt/pulls{/number}",
        "milestones_url": "https://api.github.com/repos/Aryan132005/Steller-Yellowbelt/milestones{/number}",
        "notifications_url": "https://api.github.com/repos/Aryan132005/Steller-Yellowbelt/notifications{?since,all,participating}",
        "labels_url": "https://api.github.com/repos/Aryan132005/Steller-Yellowbelt/labels{/name}",
        "releases_url": "https://api.github.com/repos/Aryan132005/Steller-Yellowbelt/releases{/id}",
        "deployments_url": "https://api.github.com/repos/Aryan132005/Steller-Yellowbelt/deployments"
      },
      "head_repository": {
        "id": 1290657800,
        "node_id": "R_kgDOTO3gCA",
        "name": "Steller-Yellowbelt",
        "full_name": "Aryan132005/Steller-Yellowbelt",
        "private": false,
        "owner": {
          "login": "Aryan132005",
          "id": 146818102,
          "node_id": "U_kgDOCMBENg",
          "avatar_url": "https://avatars.githubusercontent.com/u/146818102?v=4",
          "gravatar_id": "",
          "url": "https://api.github.com/users/Aryan132005",
          "html_url": "https://github.com/Aryan132005",
          "followers_url": "https://api.github.com/users/Aryan132005/followers",
          "following_url": "https://api.github.com/users/Aryan132005/following{/other_user}",
          "gists_url": "https://api.github.com/users/Aryan132005/gists{/gist_id}",
          "starred_url": "https://api.github.com/users/Aryan132005/starred{/owner}{/repo}",
          "subscriptions_url": "https://api.github.com/users/Aryan132005/subscriptions",
          "organizations_url": "https://api.github.com/users/Aryan132005/orgs",
          "repos_url": "https://api.github.com/users/Aryan132005/repos",
          "events_url": "https://api.github.com/users/Aryan132005/events{/privacy}",
          "received_events_url": "https://api.github.com/users/Aryan132005/received_events",
          "type": "User",
          "user_view_type": "public",
          "site_admin": false
        },
        "html_url": "https://github.com/Aryan132005/Steller-Yellowbelt",
        "description": null,
        "fork": false,
        "url": "https://api.github.com/repos/Aryan132005/Steller-Yellowbelt",
        "forks_url": "https://api.github.com/repos/Aryan132005/Steller-Yellowbelt/forks",
        "keys_url": "https://api.github.com/repos/Aryan132005/Steller-Yellowbelt/keys{/key_id}",
        "collaborators_url": "https://api.github.com/repos/Aryan132005/Steller-Yellowbelt/collaborators{/collaborator}",
        "teams_url": "https://api.github.com/repos/Aryan132005/Steller-Yellowbelt/teams",
        "hooks_url": "https://api.github.com/repos/Aryan132005/Steller-Yellowbelt/hooks",
        "issue_events_url": "https://api.github.com/repos/Aryan132005/Steller-Yellowbelt/issues/events{/number}",
        "events_url": "https://api.github.com/repos/Aryan132005/Steller-Yellowbelt/events",
        "assignees_url": "https://api.github.com/repos/Aryan132005/Steller-Yellowbelt/assignees{/user}",
        "branches_url": "https://api.github.com/repos/Aryan132005/Steller-Yellowbelt/branches{/branch}",
        "tags_url": "https://api.github.com/repos/Aryan132005/Steller-Yellowbelt/tags",
        "blobs_url": "https://api.github.com/repos/Aryan132005/Steller-Yellowbelt/git/blobs{/sha}",
        "git_tags_url": "https://api.github.com/repos/Aryan132005/Steller-Yellowbelt/git/tags{/sha}",
        "git_refs_url": "https://api.github.com/repos/Aryan132005/Steller-Yellowbelt/git/refs{/sha}",
        "trees_url": "https://api.github.com/repos/Aryan132005/Steller-Yellowbelt/git/trees{/sha}",
        "statuses_url": "https://api.github.com/repos/Aryan132005/Steller-Yellowbelt/statuses/{sha}",
        "languages_url": "https://api.github.com/repos/Aryan132005/Steller-Yellowbelt/languages",
        "stargazers_url": "https://api.github.com/repos/Aryan132005/Steller-Yellowbelt/stargazers",
        "contributors_url": "https://api.github.com/repos/Aryan132005/Steller-Yellowbelt/contributors",
        "subscribers_url": "https://api.github.com/repos/Aryan132005/Steller-Yellowbelt/subscribers",
        "subscription_url": "https://api.github.com/repos/Aryan132005/Steller-Yellowbelt/subscription",
        "commits_url": "https://api.github.com/repos/Aryan132005/Steller-Yellowbelt/commits{/sha}",
        "git_commits_url": "https://api.github.com/repos/Aryan132005/Steller-Yellowbelt/git/commits{/sha}",
        "comments_url": "https://api.github.com/repos/Aryan132005/Steller-Yellowbelt/comments{/number}",
        "issue_comment_url": "https://api.github.com/repos/Aryan132005/Steller-Yellowbelt/issues/comments{/number}",
        "contents_url": "https://api.github.com/repos/Aryan132005/Steller-Yellowbelt/contents/{+path}",
        "compare_url": "https://api.github.com/repos/Aryan132005/Steller-Yellowbelt/compare/{base}...{head}",
        "merges_url": "https://api.github.com/repos/Aryan132005/Steller-Yellowbelt/merges",
        "archive_url": "https://api.github.com/repos/Aryan132005/Steller-Yellowbelt/{archive_format}{/ref}",
        "downloads_url": "https://api.github.com/repos/Aryan132005/Steller-Yellowbelt/downloads",
        "issues_url": "https://api.github.com/repos/Aryan132005/Steller-Yellowbelt/issues{/number}",
        "pulls_url": "https://api.github.com/repos/Aryan132005/Steller-Yellowbelt/pulls{/number}",
        "milestones_url": "https://api.github.com/repos/Aryan132005/Steller-Yellowbelt/milestones{/number}",
        "notifications_url": "https://api.github.com/repos/Aryan132005/Steller-Yellowbelt/notifications{?since,all,participating}",
        "labels_url": "https://api.github.com/repos/Aryan132005/Steller-Yellowbelt/labels{/name}",
        "releases_url": "https://api.github.com/repos/Aryan132005/Steller-Yellowbelt/releases{/id}",
        "deployments_url": "https://api.github.com/repos/Aryan132005/Steller-Yellowbelt/deployments"
      }
    },
    {
      "id": 28772819113,
      "name": ".github/workflows/main.yml",
      "node_id": "WFR_kwLOTO3gCM8AAAAGsv5gqQ",
      "head_branch": "main",
      "head_sha": "8e0bc73a88d074c65b7576fafbf320cc3855a28a",
      "path": ".github/workflows/main.yml",
      "display_title": "Create main.yml",
      "run_number": 1,
      "event": "push",
      "status": "completed",
      "conclusion": "failure",
      "workflow_id": 307819953,
      "check_suite_id": 77757823882,
      "check_suite_node_id": "CS_kwDOTO3gCM8AAAASGro7ig",
      "url": "https://api.github.com/repos/Aryan132005/Steller-Yellowbelt/actions/runs/28772819113",
      "html_url": "https://github.com/Aryan132005/Steller-Yellowbelt/actions/runs/28772819113",
      "pull_requests": [

      ],
      "created_at": "2026-07-06T06:38:48Z",
      "updated_at": "2026-07-06T06:38:48Z",
      "actor": {
        "login": "Aryan132005",
        "id": 146818102,
        "node_id": "U_kgDOCMBENg",
        "avatar_url": "https://avatars.githubusercontent.com/u/146818102?v=4",
        "gravatar_id": "",
        "url": "https://api.github.com/users/Aryan132005",
        "html_url": "https://github.com/Aryan132005",
        "followers_url": "https://api.github.com/users/Aryan132005/followers",
        "following_url": "https://api.github.com/users/Aryan132005/following{/other_user}",
        "gists_url": "https://api.github.com/users/Aryan132005/gists{/gist_id}",
        "starred_url": "https://api.github.com/users/Aryan132005/starred{/owner}{/repo}",
        "subscriptions_url": "https://api.github.com/users/Aryan132005/subscriptions",
        "organizations_url": "https://api.github.com/users/Aryan132005/orgs",
        "repos_url": "https://api.github.com/users/Aryan132005/repos",
        "events_url": "https://api.github.com/users/Aryan132005/events{/privacy}",
        "received_events_url": "https://api.github.com/users/Aryan132005/received_events",
        "type": "User",
        "user_view_type": "public",
        "site_admin": false
      },
      "run_attempt": 1,
      "referenced_workflows": [

      ],
      "run_started_at": "2026-07-06T06:38:48Z",
      "triggering_actor": {
        "login": "Aryan132005",
        "id": 146818102,
        "node_id": "U_kgDOCMBENg",
        "avatar_url": "https://avatars.githubusercontent.com/u/146818102?v=4",
        "gravatar_id": "",
        "url": "https://api.github.com/users/Aryan132005",
        "html_url": "https://github.com/Aryan132005",
        "followers_url": "https://api.github.com/users/Aryan132005/followers",
        "following_url": "https://api.github.com/users/Aryan132005/following{/other_user}",
        "gists_url": "https://api.github.com/users/Aryan132005/gists{/gist_id}",
        "starred_url": "https://api.github.com/users/Aryan132005/starred{/owner}{/repo}",
        "subscriptions_url": "https://api.github.com/users/Aryan132005/subscriptions",
        "organizations_url": "https://api.github.com/users/Aryan132005/orgs",
        "repos_url": "https://api.github.com/users/Aryan132005/repos",
        "events_url": "https://api.github.com/users/Aryan132005/events{/privacy}",
        "received_events_url": "https://api.github.com/users/Aryan132005/received_events",
        "type": "User",
        "user_view_type": "public",
        "site_admin": false
      },
      "jobs_url": "https://api.github.com/repos/Aryan132005/Steller-Yellowbelt/actions/runs/28772819113/jobs",
      "logs_url": "https://api.github.com/repos/Aryan132005/Steller-Yellowbelt/actions/runs/28772819113/logs",
      "check_suite_url": "https://api.github.com/repos/Aryan132005/Steller-Yellowbelt/check-suites/77757823882",
      "artifacts_url": "https://api.github.com/repos/Aryan132005/Steller-Yellowbelt/actions/runs/28772819113/artifacts",
      "cancel_url": "https://api.github.com/repos/Aryan132005/Steller-Yellowbelt/actions/runs/28772819113/cancel",
      "rerun_url": "https://api.github.com/repos/Aryan132005/Steller-Yellowbelt/actions/runs/28772819113/rerun",
      "previous_attempt_url": null,
      "workflow_url": "https://api.github.com/repos/Aryan132005/Steller-Yellowbelt/actions/workflows/307819953",
      "head_commit": {
        "id": "8e0bc73a88d074c65b7576fafbf320cc3855a28a",
        "tree_id": "62f07b8ffa1423bcfec8789b94949473e16f2ed2",
        "message": "Create main.yml",
        "timestamp": "2026-07-06T06:38:44Z",
        "author": {
          "name": "Aryan Saini",
          "email": "146818102+Aryan132005@users.noreply.github.com"
        },
        "committer": {
          "name": "GitHub",
          "email": "noreply@github.com"
        }
      },
      "repository": {
        "id": 1290657800,
        "node_id": "R_kgDOTO3gCA",
        "name": "Steller-Yellowbelt",
        "full_name": "Aryan132005/Steller-Yellowbelt",
        "private": false,
        "owner": {
          "login": "Aryan132005",
          "id": 146818102,
          "node_id": "U_kgDOCMBENg",
          "avatar_url": "https://avatars.githubusercontent.com/u/146818102?v=4",
          "gravatar_id": "",
          "url": "https://api.github.com/users/Aryan132005",
          "html_url": "https://github.com/Aryan132005",
          "followers_url": "https://api.github.com/users/Aryan132005/followers",
          "following_url": "https://api.github.com/users/Aryan132005/following{/other_user}",
          "gists_url": "https://api.github.com/users/Aryan132005/gists{/gist_id}",
          "starred_url": "https://api.github.com/users/Aryan132005/starred{/owner}{/repo}",
          "subscriptions_url": "https://api.github.com/users/Aryan132005/subscriptions",
          "organizations_url": "https://api.github.com/users/Aryan132005/orgs",
          "repos_url": "https://api.github.com/users/Aryan132005/repos",
          "events_url": "https://api.github.com/users/Aryan132005/events{/privacy}",
          "received_events_url": "https://api.github.com/users/Aryan132005/received_events",
          "type": "User",
          "user_view_type": "public",
          "site_admin": false
        },
        "html_url": "https://github.com/Aryan132005/Steller-Yellowbelt",
        "description": null,
        "fork": false,
        "url": "https://api.github.com/repos/Aryan132005/Steller-Yellowbelt",
        "forks_url": "https://api.github.com/repos/Aryan132005/Steller-Yellowbelt/forks",
        "keys_url": "https://api.github.com/repos/Aryan132005/Steller-Yellowbelt/keys{/key_id}",
        "collaborators_url": "https://api.github.com/repos/Aryan132005/Steller-Yellowbelt/collaborators{/collaborator}",
        "teams_url": "https://api.github.com/repos/Aryan132005/Steller-Yellowbelt/teams",
        "hooks_url": "https://api.github.com/repos/Aryan132005/Steller-Yellowbelt/hooks",
        "issue_events_url": "https://api.github.com/repos/Aryan132005/Steller-Yellowbelt/issues/events{/number}",
        "events_url": "https://api.github.com/repos/Aryan132005/Steller-Yellowbelt/events",
        "assignees_url": "https://api.github.com/repos/Aryan132005/Steller-Yellowbelt/assignees{/user}",
        "branches_url": "https://api.github.com/repos/Aryan132005/Steller-Yellowbelt/branches{/branch}",
        "tags_url": "https://api.github.com/repos/Aryan132005/Steller-Yellowbelt/tags",
        "blobs_url": "https://api.github.com/repos/Aryan132005/Steller-Yellowbelt/git/blobs{/sha}",
        "git_tags_url": "https://api.github.com/repos/Aryan132005/Steller-Yellowbelt/git/tags{/sha}",
        "git_refs_url": "https://api.github.com/repos/Aryan132005/Steller-Yellowbelt/git/refs{/sha}",
        "trees_url": "https://api.github.com/repos/Aryan132005/Steller-Yellowbelt/git/trees{/sha}",
        "statuses_url": "https://api.github.com/repos/Aryan132005/Steller-Yellowbelt/statuses/{sha}",
        "languages_url": "https://api.github.com/repos/Aryan132005/Steller-Yellowbelt/languages",
        "stargazers_url": "https://api.github.com/repos/Aryan132005/Steller-Yellowbelt/stargazers",
        "contributors_url": "https://api.github.com/repos/Aryan132005/Steller-Yellowbelt/contributors",
        "subscribers_url": "https://api.github.com/repos/Aryan132005/Steller-Yellowbelt/subscribers",
        "subscription_url": "https://api.github.com/repos/Aryan132005/Steller-Yellowbelt/subscription",
        "commits_url": "https://api.github.com/repos/Aryan132005/Steller-Yellowbelt/commits{/sha}",
        "git_commits_url": "https://api.github.com/repos/Aryan132005/Steller-Yellowbelt/git/commits{/sha}",
        "comments_url": "https://api.github.com/repos/Aryan132005/Steller-Yellowbelt/comments{/number}",
        "issue_comment_url": "https://api.github.com/repos/Aryan132005/Steller-Yellowbelt/issues/comments{/number}",
        "contents_url": "https://api.github.com/repos/Aryan132005/Steller-Yellowbelt/contents/{+path}",
        "compare_url": "https://api.github.com/repos/Aryan132005/Steller-Yellowbelt/compare/{base}...{head}",
        "merges_url": "https://api.github.com/repos/Aryan132005/Steller-Yellowbelt/merges",
        "archive_url": "https://api.github.com/repos/Aryan132005/Steller-Yellowbelt/{archive_format}{/ref}",
        "downloads_url": "https://api.github.com/repos/Aryan132005/Steller-Yellowbelt/downloads",
        "issues_url": "https://api.github.com/repos/Aryan132005/Steller-Yellowbelt/issues{/number}",
        "pulls_url": "https://api.github.com/repos/Aryan132005/Steller-Yellowbelt/pulls{/number}",
        "milestones_url": "https://api.github.com/repos/Aryan132005/Steller-Yellowbelt/milestones{/number}",
        "notifications_url": "https://api.github.com/repos/Aryan132005/Steller-Yellowbelt/notifications{?since,all,participating}",
        "labels_url": "https://api.github.com/repos/Aryan132005/Steller-Yellowbelt/labels{/name}",
        "releases_url": "https://api.github.com/repos/Aryan132005/Steller-Yellowbelt/releases{/id}",
        "deployments_url": "https://api.github.com/repos/Aryan132005/Steller-Yellowbelt/deployments"
      },
      "head_repository": {
        "id": 1290657800,
        "node_id": "R_kgDOTO3gCA",
        "name": "Steller-Yellowbelt",
        "full_name": "Aryan132005/Steller-Yellowbelt",
        "private": false,
        "owner": {
          "login": "Aryan132005",
          "id": 146818102,
          "node_id": "U_kgDOCMBENg",
          "avatar_url": "https://avatars.githubusercontent.com/u/146818102?v=4",
          "gravatar_id": "",
          "url": "https://api.github.com/users/Aryan132005",
          "html_url": "https://github.com/Aryan132005",
          "followers_url": "https://api.github.com/users/Aryan132005/followers",
          "following_url": "https://api.github.com/users/Aryan132005/following{/other_user}",
          "gists_url": "https://api.github.com/users/Aryan132005/gists{/gist_id}",
          "starred_url": "https://api.github.com/users/Aryan132005/starred{/owner}{/repo}",
          "subscriptions_url": "https://api.github.com/users/Aryan132005/subscriptions",
          "organizations_url": "https://api.github.com/users/Aryan132005/orgs",
          "repos_url": "https://api.github.com/users/Aryan132005/repos",
          "events_url": "https://api.github.com/users/Aryan132005/events{/privacy}",
          "received_events_url": "https://api.github.com/users/Aryan132005/received_events",
          "type": "User",
          "user_view_type": "public",
          "site_admin": false
        },
        "html_url": "https://github.com/Aryan132005/Steller-Yellowbelt",
        "description": null,
        "fork": false,
        "url": "https://api.github.com/repos/Aryan132005/Steller-Yellowbelt",
        "forks_url": "https://api.github.com/repos/Aryan132005/Steller-Yellowbelt/forks",
        "keys_url": "https://api.github.com/repos/Aryan132005/Steller-Yellowbelt/keys{/key_id}",
        "collaborators_url": "https://api.github.com/repos/Aryan132005/Steller-Yellowbelt/collaborators{/collaborator}",
        "teams_url": "https://api.github.com/repos/Aryan132005/Steller-Yellowbelt/teams",
        "hooks_url": "https://api.github.com/repos/Aryan132005/Steller-Yellowbelt/hooks",
        "issue_events_url": "https://api.github.com/repos/Aryan132005/Steller-Yellowbelt/issues/events{/number}",
        "events_url": "https://api.github.com/repos/Aryan132005/Steller-Yellowbelt/events",
        "assignees_url": "https://api.github.com/repos/Aryan132005/Steller-Yellowbelt/assignees{/user}",
        "branches_url": "https://api.github.com/repos/Aryan132005/Steller-Yellowbelt/branches{/branch}",
        "tags_url": "https://api.github.com/repos/Aryan132005/Steller-Yellowbelt/tags",
        "blobs_url": "https://api.github.com/repos/Aryan132005/Steller-Yellowbelt/git/blobs{/sha}",
        "git_tags_url": "https://api.github.com/repos/Aryan132005/Steller-Yellowbelt/git/tags{/sha}",
        "git_refs_url": "https://api.github.com/repos/Aryan132005/Steller-Yellowbelt/git/refs{/sha}",
        "trees_url": "https://api.github.com/repos/Aryan132005/Steller-Yellowbelt/git/trees{/sha}",
        "statuses_url": "https://api.github.com/repos/Aryan132005/Steller-Yellowbelt/statuses/{sha}",
        "languages_url": "https://api.github.com/repos/Aryan132005/Steller-Yellowbelt/languages",
        "stargazers_url": "https://api.github.com/repos/Aryan132005/Steller-Yellowbelt/stargazers",
        "contributors_url": "https://api.github.com/repos/Aryan132005/Steller-Yellowbelt/contributors",
        "subscribers_url": "https://api.github.com/repos/Aryan132005/Steller-Yellowbelt/subscribers",
        "subscription_url": "https://api.github.com/repos/Aryan132005/Steller-Yellowbelt/subscription",
        "commits_url": "https://api.github.com/repos/Aryan132005/Steller-Yellowbelt/commits{/sha}",
        "git_commits_url": "https://api.github.com/repos/Aryan132005/Steller-Yellowbelt/git/commits{/sha}",
        "comments_url": "https://api.github.com/repos/Aryan132005/Steller-Yellowbelt/comments{/number}",
        "issue_comment_url": "https://api.github.com/repos/Aryan132005/Steller-Yellowbelt/issues/comments{/number}",
        "contents_url": "https://api.github.com/repos/Aryan132005/Steller-Yellowbelt/contents/{+path}",
        "compare_url": "https://api.github.com/repos/Aryan132005/Steller-Yellowbelt/compare/{base}...{head}",
        "merges_url": "https://api.github.com/repos/Aryan132005/Steller-Yellowbelt/merges",
        "archive_url": "https://api.github.com/repos/Aryan132005/Steller-Yellowbelt/{archive_format}{/ref}",
        "downloads_url": "https://api.github.com/repos/Aryan132005/Steller-Yellowbelt/downloads",
        "issues_url": "https://api.github.com/repos/Aryan132005/Steller-Yellowbelt/issues{/number}",
        "pulls_url": "https://api.github.com/repos/Aryan132005/Steller-Yellowbelt/pulls{/number}",
        "milestones_url": "https://api.github.com/repos/Aryan132005/Steller-Yellowbelt/milestones{/number}",
        "notifications_url": "https://api.github.com/repos/Aryan132005/Steller-Yellowbelt/notifications{?since,all,participating}",
        "labels_url": "https://api.github.com/repos/Aryan132005/Steller-Yellowbelt/labels{/name}",
        "releases_url": "https://api.github.com/repos/Aryan132005/Steller-Yellowbelt/releases{/id}",
        "deployments_url": "https://api.github.com/repos/Aryan132005/Steller-Yellowbelt/deployments"
      }
    }
  ]
}
